freq_ope/__init__.py
freq_ope/aes.py
freq_ope/client.py
freq_ope/key.py
freq_ope/server.py
freq_ope/tree.py
freq_ope-1.0.2.dist-info/LICENSE
freq_ope-1.0.2.dist-info/METADATA
freq_ope-1.0.2.dist-info/WHEEL
freq_ope-1.0.2.dist-info/top_level.txt
freq_ope-1.0.2.dist-info/RECORD
